{
  "display": {
    "title": "Bobby_land",
    "favicon": "favicon_asset",
    "navmapThumbnail": "scene-thumbnail.png"
  },
  "owner": "",
  "contact": {
    "name": "Architectstelio#2213",
    "email": ""
  },
  "main": "bin/game.js",
  "tags": [],
  "scene": {
    "parcels": [
      "0,0"
    ],
    "base": "0,0"
  },
  "communications": {
    "type": "webrtc",
    "signalling": "https://signalling-01.decentraland.org"
  },
  "policy": {
    "contentRating": "N",
    "fly": true,
    "voiceEnabled": true,
    "blacklist": [],
    "teleportPosition": ""
  },
  "source": {
    "version": 1,
    "origin": "builder",
    "projectId": "42203220-319b-4744-bb88-2077b1a758b0",
    "point": {
      "x": 0,
      "y": 0
    },
    "rotation": "north",
    "layout": {
      "rows": 1,
      "cols": 1
    }
  }
}